Workbook

Sheet Project Instructions
A1: PR. Final Project - "Data Intelligence Dashboard"
A2: Dataset: Use the 'Final Project Dataset' sheet containing 200+ records of customer transactions. Objective: Create a full-fledged analysis and reporting solution using Excel to analyze customer transactions, find insights, and build visualizations and dashboards. Key Topics to Implement: - Date & Time Functions: TODAY, NOW, DATEDIF, EOMONTH - FILTER Function for multi-value returns - Conditional Formatting with Icons/Arrows - Create Timestamp (using NOW and iterative calculations) - WHAT-IF Analysis: Scenario Manager, Goal Seek - Linear Regression using Data Analysis Toolpak - Data Analysis & Storytelling from the dataset - Use GroupBy concepts to find High-Value Customers using formulas - Create Dashboard using: - Pivot Tables - Pivot Charts (Bar, Line, Pie) - Slicers and Timelines - KPI Indicators with Conditional Formatting - Find most frequently purchased product or repeating names using formulas - Compare two lists and extract matching names in a new column - Create Abbreviations using TEXT functions - Build a final report with insights and storytelling Deliverable: - Well-structured workbook with multiple sheets (Raw Data, Analysis, Visualizations, Dashboard) - Summary Insights with key metrics: Total Revenue, Top Customers, Most Sold Products, Regional Sales - Use of all required formulas and functions as listed above

Sheet DashBoard
A1: DashBoard
H5: Region | I5: Sum of Quantity | Q5: Category | R5: Sum of Sales
H6: Central | I6: 166 | Q6: Appliances | R6: 8338.74
H7: East | I7: 161 | Q7: Electronics | R7: 171756.05
H8: North | I8: 169 | Q8: Furniture | R8: 49097.68
H9: South | I9: 125 | Q9: Grand Total | R9: 229192.47
H10: West | I10: 132
H11: Grand Total | I11: 753
T20: Product_Name | U20: Sum of Sales
I21: Region | J21: Sum of Sales | T21: Blender | U21: 5219.13
I22: Central | J22: 41288.34 | T22: Bookshelf | U22: 15298.98
I23: East | J23: 59288.39 | T23: Coffee Maker | U23: 3119.61
I24: North | J24: 50808.31 | T24: Desk | U24: 23399.22
I25: South | J25: 36398.75 | T25: Headphones | U25: 7049.53
I26: West | J26: 41408.68 | T26: Keyboard | U26: 8009.11
I27: Grand Total | J27: 229192.47 | T27: Laptop | U27: 67499.25
T28: Monitor | U28: 21999.12
T29: Office Chair | U29: 10399.48
T30: Smartphone | U30: 67199.04
T31: Grand Total | U31: 229192.47

Sheet Quantity by Region
A3: Region | B3: Sum of Quantity
A4: Central | B4: 166
A5: East | B5: 161
A6: North | B6: 169
A7: South | B7: 125
A8: West | B8: 132
A9: Grand Total | B9: 753

Sheet Customer Segment by Sales
A3: Category | B3: Sum of Sales
A4: Appliances | B4: 8338.74
A5: Electronics | B5: 171756.05
A6: Furniture | B6: 49097.68
A7: Grand Total | B7: 229192.47

Sheet Sales by Region
A3: Region | B3: Sum of Sales
A4: Central | B4: 41288.34
A5: East | B5: 59288.39
A6: North | B6: 50808.31
A7: South | B7: 36398.75
A8: West | B8: 41408.68
A9: Grand Total | B9: 229192.47

Sheet Sales of Product
A3: Product_Name | B3: Sum of Sales
A4: Blender | B4: 5219.13
A5: Bookshelf | B5: 15298.98
A6: Coffee Maker | B6: 3119.61
A7: Desk | B7: 23399.22
A8: Headphones | B8: 7049.53
A9: Keyboard | B9: 8009.11
A10: Laptop | B10: 67499.25
A11: Monitor | B11: 21999.12
A12: Office Chair | B12: 10399.48
A13: Smartphone | B13: 67199.04
A14: Grand Total | B14: 229192.47

Sheet Final Project Dataset
A1: Transaction_ID | B1: Date | C1: Customer_ID | D1: Customer_Name | E1: Product_ID | F1: Product_Name | G1: Category | H1: Quantity | I1: Unit_Price | J1: Payment_Method | K1: Region | L1: Customer_Segment | M1: Customer_Since | N1: Sales | O1: Month | P1: Year | R1: FILTERING
A2: TRX0155 | B2: 45393 | C2: CUST023 | D2: Paul Baker | E2: P009 | F2: Monitor | G2: Electronics | H2: 3 | I2: 249.99 | J2: Cash | K2: Central | L2: Basic | M2: 44425 | N2: 749.97 | O2: =MONTH(Table1[[#This Row],[Date]]) -> 4 | P2: =YEAR(Table1[[#This Row],[Date]]) -> 2024
A3: TRX0023 | B3: 45396 | C3: CUST013 | D3: Joseph Jackson | E3: P009 | F3: Monitor | G3: Electronics | H3: 3 | I3: 249.99 | J3: Credit Card | K3: Central | L3: Premium | M3: 44575 | N3: 749.97 | O3: =MONTH(Table1[[#This Row],[Date]]) -> 4 | P3: =YEAR(Table1[[#This Row],[Date]]) -> 2024 | R3: {=_xlfn._xlws.FILTER(A2:P251,(L2:L251="Basic"))} -> TRX0155 | S3: 45393 | T3: CUST023 | U3: Paul Baker | V3: P009 | W3: Monitor | X3: Electronics | Y3: 3 | Z3: 249.99 | AA3: Cash | AB3: Central | AC3: Basic | AD3: 44425 | AE3: 749.97 | AF3: 4 | AG3: 2024
A4: TRX0139 | B4: 45399 | C4: CUST021 | D4: Kevin Scott | E4: P005 | F4: Blender | G4: Appliances | H4: 3 | I4: 59.99 | J4: PayPal | K4: South | L4: Standard | M4: 45262 | N4: 179.97 | O4: =MONTH(Table1[[#This Row],[Date]]) -> 4 | P4: =YEAR(Table1[[#This Row],[Date]]) -> 2024 | R4: TRX0240 | S4: 45403 | T4: CUST017 | U4: Charles Allen | V4: P005 | W4: Blender | X4: Appliances | Y4: 3 | Z4: 59.99 | AA4: Debit Card | AB4: South | AC4: Basic | AD4: 45007 | AE4: 179.97 | AF4: 4 | AG4: 2024
A5: TRX0043 | B5: 45400 | C5: CUST046 | D5: Kathleen Bennett | E5: P005 | F5: Blender | G5: Appliances | H5: 3 | I5: 59.99 | J5: Cash | K5: North | L5: Premium | M5: 45114 | N5: 179.97 | O5: =MONTH(Table1[[#This Row],[Date]]) -> 4 | P5: =YEAR(Table1[[#This Row],[Date]]) -> 2024 | R5: TRX0209 | S5: 45408 | T5: CUST046 | U5: Kathleen Bennett | V5: P008 | W5: Bookshelf | X5: Furniture | Y5: 5 | Z5: 149.99 | AA5: Debit Card | AB5: North | AC5: Basic | AD5: 44830 | AE5: 749.95 | AF5: 4 | AG5: 2024
A6: TRX0212 | B6: 45400 | C6: CUST003 | D6: Michael Brown | E6: P008 | F6: Bookshelf | G6: Furniture | H6: 5 | I6: 149.99 | J6: Credit Card | K6: North | L6: Premium | M6: 45295 | N6: 749.95 | O6: =MONTH(Table1[[#This Row],[Date]]) -> 4 | P6: =YEAR(Table1[[#This Row],[Date]]) -> 2024 | R6: TRX0191 | S6: 45409 | T6: CUST038 | U6: Michelle Rogers | V6: P002 | W6: Smartphone | X6: Electronics | Y6: 3 | Z6: 699.99 | AA6: Credit Card | AB6: West | AC6: Basic | AD6: 44577 | AE6: 2099.97 | AF6: 4 | AG6: 2024
A7: TRX0092 | B7: 45403 | C7: CUST024 | D7: Dorothy Nelson | E7: P005 | F7: Blender | G7: Appliances | H7: 2 | I7: 59.99 | J7: Cash | K7: West | L7: Standard | M7: 44746 | N7: 119.98 | O7: =MONTH(Table1[[#This Row],[Date]]) -> 4 | P7: =YEAR(Table1[[#This Row],[Date]]) -> 2024 | R7: TRX0134 | S7: 45410 | T7: CUST010 | U7: Maria Garcia | V7: P002 | W7: Smartphone | X7: Electronics | Y7: 2 | Z7: 699.99 | AA7: Cash | AB7: North | AC7: Basic | AD7: 44781 | AE7: 1399.98 | AF7: 4 | AG7: 2024
A8: TRX0193 | B8: 45403 | C8: CUST024 | D8: Dorothy Nelson | E8: P003 | F8: Headphones | G8: Electronics | H8: 5 | I8: 149.99 | J8: Credit Card | K8: Central | L8: Standard | M8: 44418 | N8: 749.95 | O8: =MONTH(Table1[[#This Row],[Date]]) -> 4 | P8: =YEAR(Table1[[#This Row],[Date]]) -> 2024 | R8: TRX0231 | S8: 45412 | T8: CUST018 | U8: Barbara Young | V8: P002 | W8: Smartphone | X8: Electronics | Y8: 5 | Z8: 699.99 | AA8: Cash | AB8: West | AC8: Basic | AD8: 45167 | AE8: 3499.95 | AF8: 4 | AG8: 2024
A9: TRX0240 | B9: 45403 | C9: CUST017 | D9: Charles Allen | E9: P005 | F9: Blender | G9: Appliances | H9: 3 | I9: 59.99 | J9: Debit Card | K9: South | L9: Basic | M9: 45007 | N9: 179.97 | O9: =MONTH(Table1[[#This Row],[Date]]) -> 4 | P9: =YEAR(Table1[[#This Row],[Date]]) -> 2024 | R9: TRX0040 | S9: 45424 | T9: CUST022 | U9: Susan Green | V9: P007 | W9: Desk | X9: Furniture | Y9: 5 | Z9: 299.99 | AA9: PayPal | AB9: East | AC9: Basic | AD9: 45168 | AE9: 1499.95 | AF9: 5 | AG9: 2024
A10: TRX0135 | B10: 45405 | C10: CUST009 | D10: Robert Thomas | E10: P001 | F10: Laptop | G10: Electronics | H10: 3 | I10: 899.99 | J10: PayPal | K10: East | L10: Standard | M10: 45299 | N10: 2699.97 | O10: =MONTH(Table1[[#This Row],[Date]]) -> 4 | P10: =YEAR(Table1[[#This Row],[Date]]) -> 2024 | R10: TRX0194 | S10: 45428 | T10: CUST006 | U10: Lisa Anderson | V10: P008 | W10: Bookshelf | X10: Furniture | Y10: 2 | Z10: 149.99 | AA10: Credit Card | AB10: West | AC10: Basic | AD10: 44823 | AE10: 299.98 | AF10: 5 | AG10: 2024
A11: TRX0185 | B11: 45408 | C11: CUST026 | D11: Karen Hill | E11: P005 | F11: Blender | G11: Appliances | H11: 3 | I11: 59.99 | J11: Cash | K11: West | L11: Premium | M11: 45207 | N11: 179.97 | O11: =MONTH(Table1[[#This Row],[Date]]) -> 4 | P11: =YEAR(Table1[[#This Row],[Date]]) -> 2024 | R11: TRX0232 | S11: 45434 | T11: CUST012 | U11: Patricia Moore | V11: P007 | W11: Desk | X11: Furniture | Y11: 3 | Z11: 299.99 | AA11: Credit Card | AB11: East | AC11: Basic | AD11: 44824 | AE11: 899.97 | AF11: 5 | AG11: 2024
A12: TRX0138 | B12: 45408 | C12: CUST022 | D12: Susan Green | E12: P008 | F12: Bookshelf | G12: Furniture | H12: 1 | I12: 149.99 | J12: Credit Card | K12: West | L12: Standard | M12: 45103 | N12: 149.99 | O12: =MONTH(Table1[[#This Row],[Date]]) -> 4 | P12: =YEAR(Table1[[#This Row],[Date]]) -> 2024 | R12: TRX0021 | S12: 45435 | T12: CUST006 | U12: Lisa Anderson | V12: P004 | W12: Coffee Maker | X12: Appliances | Y12: 3 | Z12: 79.99 | AA12: Cash | AB12: South | AC12: Basic | AD12: 45046 | AE12: 239.97 | AF12: 5 | AG12: 2024
A13: TRX0209 | B13: 45408 | C13: CUST046 | D13: Kathleen Bennett | E13: P008 | F13: Bookshelf | G13: Furniture | H13: 5 | I13: 149.99 | J13: Debit Card | K13: North | L13: Basic | M13: 44830 | N13: 749.95 | O13: =MONTH(Table1[[#This Row],[Date]]) -> 4 | P13: =YEAR(Table1[[#This Row],[Date]]) -> 2024 | R13: TRX0128 | S13: 45444 | T13: CUST040 | U13: Sharon Butler | V13: P005 | W13: Blender | X13: Appliances | Y13: 2 | Z13: 59.99 | AA13: Cash | AB13: West | AC13: Basic | AD13: 45390 | AE13: 119.98 | AF13: 6 | AG13: 2024
A14: TRX0246 | B14: 45408 | C14: CUST041 | D14: Peter Richardson | E14: P008 | F14: Bookshelf | G14: Furniture | H14: 3 | I14: 149.99 | J14: Cash | K14: North | L14: Premium | M14: 44806 | N14: 449.97 | O14: =MONTH(Table1[[#This Row],[Date]]) -> 4 | P14: =YEAR(Table1[[#This Row],[Date]]) -> 2024 | R14: TRX0117 | S14: 45444 | T14: CUST017 | U14: Charles Allen | V14: P010 | W14: Keyboard | X14: Electronics | Y14: 1 | Z14: 89.99 | AA14: Cash | AB14: North | AC14: Basic | AD14: 45141 | AE14: 89.99 | AF14: 6 | AG14: 2024
A15: TRX0067 | B15: 45409 | C15: CUST043 | D15: Dennis Gray | E15: P005 | F15: Blender | G15: Appliances | H15: 3 | I15: 59.99 | J15: Credit Card | K15: North | L15: Standard | M15: 45351 | N15: 179.97 | O15: =MONTH(Table1[[#This Row],[Date]]) -> 4 | P15: =YEAR(Table1[[#This Row],[Date]]) -> 2024 | R15: TRX0025 | S15: 45468 | T15: CUST049 | U15: Raymond Ross | V15: P010 | W15: Keyboard | X15: Electronics | Y15: 4 | Z15: 89.99 | AA15: Debit Card | AB15: South | AC15: Basic | AD15: 45281 | AE15: 359.96 | AF15: 6 | AG15: 2024
... A76: TRX0244 | B76: 45497 | C76: CUST013 | D76: Joseph Jackson | E76: P001 | F76: Laptop | G76: Electronics | H76: 5 | I76: 899.99 | J76: Debit Card | K76: South | L76: Standard | M76: 44899 | N76: 4499.95 | O76: =MONTH(Table1[[#This Row],[Date]]) -> 7 | P76: =YEAR(Table1[[#This Row],[Date]]) -> 2024 | R76: TRX0103 | S76: 45758 | T76: CUST039 | U76: Lawrence Reed | V76: P010 | W76: Keyboard | X76: Electronics | Y76: 2 | Z76: 89.99 | AA76: Debit Card | AB76: East | AC76: Basic | AD76: 45088 | AE76: 179.98 | AF76: 4 | AG76: 2025
A77: TRX0006 | B77: 45498 | C77: CUST007 | D77: David Martinez | E77: P005 | F77: Blender | G77: Appliances | H77: 2 | I77: 59.99 | J77: Cash | K77: North | L77: Standard | M77: 45152 | N77: 119.98 | O77: =MONTH(Table1[[#This Row],[Date]]) -> 7 | P77: =YEAR(Table1[[#This Row],[Date]]) -> 2024
A78: TRX0215 | B78: 45498 | C78: CUST047 | D78: Gerald Murphy | E78: P009 | F78: Monitor | G78: Electronics | H78: 4 | I78: 249.99 | J78: Debit Card | K78: Central | L78: Standard | M78: 45127 | N78: 999.96 | O78: =MONTH(Table1[[#This Row],[Date]]) -> 7 | P78: =YEAR(Table1[[#This Row],[Date]]) -> 2024
A79: TRX0080 | B79: 45500 | C79: CUST018 | D79: Barbara Young | E79: P009 | F79: Monitor | G79: Electronics | H79: 2 | I79: 249.99 | J79: Cash | K79: North | L79: Premium | M79: 45164 | N79: 499.98 | O79: =MONTH(Table1[[#This Row],[Date]]) -> 7 | P79: =YEAR(Table1[[#This Row],[Date]]) -> 2024
A80: TRX0228 | B80: 45500 | C80: CUST019 | D80: Daniel King | E80: P007 | F80: Desk | G80: Furniture | H80: 1 | I80: 299.99 | J80: Cash | K80: South | L80: Basic | M80: 44982 | N80: 299.99 | O80: =MONTH(Table1[[#This Row],[Date]]) -> 7 | P80: =YEAR(Table1[[#This Row],[Date]]) -> 2024
A81: TRX0157 | B81: 45501 | C81: CUST025 | D81: Mark Carter | E81: P010 | F81: Keyboard | G81: Electronics | H81: 2 | I81: 89.99 | J81: PayPal | K81: South | L81: Basic | M81: 44976 | N81: 179.98 | O81: =MONTH(Table1[[#This Row],[Date]]) -> 7 | P81: =YEAR(Table1[[#This Row],[Date]]) -> 2024
A82: TRX0002 | B82: 45501 | C82: CUST019 | D82: Daniel King | E82: P007 | F82: Desk | G82: Furniture | H82: 3 | I82: 299.99 | J82: Cash | K82: Central | L82: Basic | M82: 44732 | N82: 899.97 | O82: =MONTH(Table1[[#This Row],[Date]]) -> 7 | P82: =YEAR(Table1[[#This Row],[Date]]) -> 2024
A83: TRX0217 | B83: 45503 | C83: CUST025 | D83: Mark Carter | E83: P002 | F83: Smartphone | G83: Electronics | H83: 2 | I83: 699.99 | J83: Credit Card | K83: North | L83: Premium | M83: 44999 | N83: 1399.98 | O83: =MONTH(Table1[[#This Row],[Date]]) -> 7 | P83: =YEAR(Table1[[#This Row],[Date]]) -> 2024
A84: TRX0249 | B84: 45504 | C84: CUST030 | D84: Helen Roberts | E84: P001 | F84: Laptop | G84: Electronics | H84: 4 | I84: 899.99 | J84: Debit Card | K84: South | L84: Standard | M84: 44523 | N84: 3599.96 | O84: =MONTH(Table1[[#This Row],[Date]]) -> 7 | P84: =YEAR(Table1[[#This Row],[Date]]) -> 2024
A85: TRX0065 | B85: 45509 | C85: CUST016 | D85: Elizabeth Hall | E85: P008 | F85: Bookshelf | G85: Furniture | H85: 2 | I85: 149.99 | J85: Credit Card | K85: West | L85: Basic | M85: 44542 | N85: 299.98 | O85: =MONTH(Table1[[#This Row],[Date]]) -> 8 | P85: =YEAR(Table1[[#This Row],[Date]]) -> 2024
A86: TRX0176 | B86: 45510 | C86: CUST044 | D86: Cynthia Price | E86: P008 | F86: Bookshelf | G86: Furniture | H86: 2 | I86: 149.99 | J86: Debit Card | K86: East | L86: Standard | M86: 44667 | N86: 299.98 | O86: =MONTH(Table1[[#This Row],[Date]]) -> 8 | P86: =YEAR(Table1[[#This Row],[Date]]) -> 2024
A87: TRX0101 | B87: 45513 | C87: CUST010 | D87: Maria Garcia | E87: P010 | F87: Keyboard | G87: Electronics | H87: 1 | I87: 89.99 | J87: Credit Card | K87: North | L87: Standard | M87: 45393 | N87: 89.99 | O87: =MONTH(Table1[[#This Row],[Date]]) -> 8 | P87: =YEAR(Table1[[#This Row],[Date]]) -> 2024
A88: TRX0205 | B88: 45515 | C88: CUST025 | D88: Mark Carter | E88: P007 | F88: Desk | G88: Furniture | H88: 5 | I88: 299.99 | J88: Credit Card | K88: North | L88: Basic | M88: 44965 | N88: 1499.95 | O88: =MONTH(Table1[[#This Row],[Date]]) -> 8 | P88: =YEAR(Table1[[#This Row],[Date]]) -> 2024
... A251: TRX0064 | B251: 45758 | C251: CUST031 | D251: Steven Turner | E251: P010 | F251: Keyboard | G251: Electronics | H251: 3 | I251: 89.99 | J251: Debit Card | K251: North | L251: Premium | M251: 44878 | N251: 269.97 | O251: =MONTH(Table1[[#This Row],[Date]]) -> 4 | P251: =YEAR(Table1[[#This Row],[Date]]) -> 2025

Sheet Sales Analysis
A1: Customer Id | B1: Customer Name | C1: Total Sales | D1: Region | E1: Region wise Total Sales | G1: Products | H1: Total Sales Product Wise | J1: Category | K1: Total Sales Category Wise | M1: Payment Method | N1: Total SalesThrough Payment Method
A2: {=_xlfn.UNIQUE('Final Project Dataset'!C2:C251)} -> CUST023 | B2: {=_xlfn.UNIQUE('Final Project Dataset'!D2:D251)} -> Paul Baker | C2: =SUMIF('Final Project Dataset'!C2:C251,A2,'Final Project Dataset'!N2:N251) -> 8309.74 | D2: {=_xlfn.UNIQUE('Final Project Dataset'!K2:K251)} -> Central | E2: =SUMIF('Final Project Dataset'!K2:K251,D2,'Final Project Dataset'!N2:N251) -> 41288.34 | G2: {=_xlfn.UNIQUE('Final Project Dataset'!F2:F251)} -> Monitor | H2: =SUMIF('Final Project Dataset'!F2:F251,G2,'Final Project Dataset'!N2:N251) -> 21999.12 | J2: {=_xlfn.UNIQUE('Final Project Dataset'!G2:G251)} -> Electronics | K2: =SUMIF('Final Project Dataset'!G2:G251,J2,'Final Project Dataset'!N2:N251) -> 171756.05 | M2: {=_xlfn.UNIQUE('Final Project Dataset'!J2:J251)} -> Cash | N2: =SUMIF('Final Project Dataset'!J2:J251,M2,'Final Project Dataset'!N2:N251) -> 57427.79
A3: CUST013 | B3: Joseph Jackson | C3: =SUMIF('Final Project Dataset'!C3:C252,A3,'Final Project Dataset'!N3:N252) -> 6949.84 | D3: South | E3: =SUMIF('Final Project Dataset'!K3:K252,D3,'Final Project Dataset'!N3:N252) -> 36398.75 | G3: Blender | H3: =SUMIF('Final Project Dataset'!F3:F252,G3,'Final Project Dataset'!N3:N252) -> 5219.13 | J3: Appliances | K3: =SUMIF('Final Project Dataset'!G3:G252,J3,'Final Project Dataset'!N3:N252) -> 8338.74 | M3: Credit Card | N3: =SUMIF('Final Project Dataset'!J3:J252,M3,'Final Project Dataset'!N3:N252) -> 61447.96
A4: CUST021 | B4: Kevin Scott | C4: =SUMIF('Final Project Dataset'!C4:C253,A4,'Final Project Dataset'!N4:N253) -> 3259.87 | D4: North | E4: =SUMIF('Final Project Dataset'!K4:K253,D4,'Final Project Dataset'!N4:N253) -> 50808.31 | G4: Bookshelf | H4: =SUMIF('Final Project Dataset'!F4:F253,G4,'Final Project Dataset'!N4:N253) -> 15298.98 | J4: Furniture | K4: =SUMIF('Final Project Dataset'!G4:G253,J4,'Final Project Dataset'!N4:N253) -> 49097.68 | M4: PayPal | N4: =SUMIF('Final Project Dataset'!J4:J253,M4,'Final Project Dataset'!N4:N253) -> 58198.41
A5: CUST046 | B5: Kathleen Bennett | C5: =SUMIF('Final Project Dataset'!C5:C254,A5,'Final Project Dataset'!N5:N254) -> 4309.81 | D5: West | E5: =SUMIF('Final Project Dataset'!K5:K254,D5,'Final Project Dataset'!N5:N254) -> 41408.68 | G5: Headphones | H5: =SUMIF('Final Project Dataset'!F5:F254,G5,'Final Project Dataset'!N5:N254) -> 7049.53 | J5: Total | K5: =SUM(K2:L4) -> 229192.47 | M5: Debit Card | N5: =SUMIF('Final Project Dataset'!J5:J254,M5,'Final Project Dataset'!N5:N254) -> 52118.31
A6: CUST003 | B6: Michael Brown | C6: =SUMIF('Final Project Dataset'!C6:C255,A6,'Final Project Dataset'!N6:N255) -> 6169.74 | D6: East | E6: =SUMIF('Final Project Dataset'!K6:K255,D6,'Final Project Dataset'!N6:N255) -> 59288.39 | G6: Laptop | H6: =SUMIF('Final Project Dataset'!F6:F255,G6,'Final Project Dataset'!N6:N255) -> 67499.25 | M6: Total | N6: =SUM(N2:O5) -> 229192.47
A7: CUST024 | B7: Dorothy Nelson | C7: =SUMIF('Final Project Dataset'!C7:C256,A7,'Final Project Dataset'!N7:N256) -> 8269.79 | D7: Total | E7: =SUM(E2:F6) -> 229192.47 | G7: Smartphone | H7: =SUMIF('Final Project Dataset'!F7:F256,G7,'Final Project Dataset'!N7:N256) -> 67199.04
A8: CUST017 | B8: Charles Allen | C8: =SUMIF('Final Project Dataset'!C8:C257,A8,'Final Project Dataset'!N8:N257) -> 5089.73 | G8: Desk | H8: =SUMIF('Final Project Dataset'!F8:F257,G8,'Final Project Dataset'!N8:N257) -> 23399.22
A9: CUST009 | B9: Robert Thomas | C9: =SUMIF('Final Project Dataset'!C9:C258,A9,'Final Project Dataset'!N9:N258) -> 3509.9 | G9: Coffee Maker | H9: =SUMIF('Final Project Dataset'!F9:F258,G9,'Final Project Dataset'!N9:N258) -> 3119.61
A10: CUST026 | B10: Karen Hill | C10: =SUMIF('Final Project Dataset'!C10:C259,A10,'Final Project Dataset'!N10:N259) -> 8009.77 | G10: Keyboard | H10: =SUMIF('Final Project Dataset'!F10:F259,G10,'Final Project Dataset'!N10:N259) -> 8009.11
A11: CUST022 | B11: Susan Green | C11: =SUMIF('Final Project Dataset'!C11:C260,A11,'Final Project Dataset'!N11:N260) -> 1979.89 | G11: Office Chair | H11: =SUMIF('Final Project Dataset'!F11:F260,G11,'Final Project Dataset'!N11:N260) -> 10399.48
A12: CUST041 | B12: Peter Richardson | C12: =SUMIF('Final Project Dataset'!C12:C261,A12,'Final Project Dataset'!N12:N261) -> 5949.85 | G12: Total | H12: =SUM(H2:I11) -> 229192.47
A13: CUST043 | B13: Dennis Gray | C13: =SUMIF('Final Project Dataset'!C13:C262,A13,'Final Project Dataset'!N13:N262) -> 479.92
A14: CUST038 | B14: Michelle Rogers | C14: =SUMIF('Final Project Dataset'!C14:C263,A14,'Final Project Dataset'!N14:N263) -> 4199.94
A15: CUST027 | B15: George Adams | C15: =SUMIF('Final Project Dataset'!C15:C264,A15,'Final Project Dataset'!N15:N264) -> 3779.93
A16: CUST025 | B16: Mark Carter | C16: =SUMIF('Final Project Dataset'!C16:C265,A16,'Final Project Dataset'!N16:N265) -> 15659.65
A17: CUST010 | B17: Maria Garcia | C17: =SUMIF('Final Project Dataset'!C17:C266,A17,'Final Project Dataset'!N17:N266) -> 1909.93
A18: CUST048 | B18: Virginia Sanders | C18: =SUMIF('Final Project Dataset'!C18:C267,A18,'Final Project Dataset'!N18:N267) -> 4789.79
A19: CUST018 | B19: Barbara Young | C19: =SUMIF('Final Project Dataset'!C19:C268,A19,'Final Project Dataset'!N19:N268) -> 10649.8
A20: CUST012 | B20: Patricia Moore | C20: =SUMIF('Final Project Dataset'!C20:C269,A20,'Final Project Dataset'!N20:N269) -> 9799.73
A21: CUST044 | B21: Cynthia Price | C21: =SUMIF('Final Project Dataset'!C21:C270,A21,'Final Project Dataset'!N21:N270) -> 3769.83
A22: CUST036 | B22: Nancy Collins | C22: =SUMIF('Final Project Dataset'!C22:C271,A22,'Final Project Dataset'!N22:N271) -> 4189.77
A23: CUST014 | B23: Linda Martin | C23: =SUMIF('Final Project Dataset'!C23:C272,A23,'Final Project Dataset'!N23:N272) -> 1289.9
A24: CUST030 | B24: Helen Roberts | C24: =SUMIF('Final Project Dataset'!C24:C273,A24,'Final Project Dataset'!N24:N273) -> 6459.79
... A51: CUST001 | B51: John Smith | C51: =SUMIF('Final Project Dataset'!C51:C300,A51,'Final Project Dataset'!N51:N300) -> 599.96
A52: Total | C52: =SUM(C2:C51) -> 229192.47

Sheet WHAT-IF Analysis
A1: Scenario Manager
A3: Input (DISCOUNT) | B3: Output ( TOTAL SALES ) | C3: Sales as per Discount
A4: 0.03 | B4: =SUM(C4:C253) -> 222316.7 | C4: ='Final Project Dataset'!N2*(1-'WHAT-IF Analysis'!$A$4) -> 727.4709
C5: ='Final Project Dataset'!N3*(1-'WHAT-IF Analysis'!$A$4) -> 727.4709
C6: ='Final Project Dataset'!N4*(1-'WHAT-IF Analysis'!$A$4) -> 174.5709
C7: ='Final Project Dataset'!N5*(1-'WHAT-IF Analysis'!$A$4) -> 174.5709
C8: ='Final Project Dataset'!N6*(1-'WHAT-IF Analysis'!$A$4) -> 727.4515
C9: ='Final Project Dataset'!N7*(1-'WHAT-IF Analysis'!$A$4) -> 116.3806
C10: ='Final Project Dataset'!N8*(1-'WHAT-IF Analysis'!$A$4) -> 727.4515
C11: ='Final Project Dataset'!N9*(1-'WHAT-IF Analysis'!$A$4) -> 174.5709
C12: ='Final Project Dataset'!N10*(1-'WHAT-IF Analysis'!$A$4) -> 2618.9709
C13: ='Final Project Dataset'!N11*(1-'WHAT-IF Analysis'!$A$4) -> 174.5709
C14: ='Final Project Dataset'!N12*(1-'WHAT-IF Analysis'!$A$4) -> 145.4903
C15: ='Final Project Dataset'!N13*(1-'WHAT-IF Analysis'!$A$4) -> 727.4515
C16: ='Final Project Dataset'!N14*(1-'WHAT-IF Analysis'!$A$4) -> 436.4709
... C253: ='Final Project Dataset'!N251*(1-'WHAT-IF Analysis'!$A$4) -> 261.8709
